README.rst
setup.py
aio/__init__.py
aio.http.server.egg-info/PKG-INFO
aio.http.server.egg-info/SOURCES.txt
aio.http.server.egg-info/dependency_links.txt
aio.http.server.egg-info/namespace_packages.txt
aio.http.server.egg-info/not-zip-safe
aio.http.server.egg-info/requires.txt
aio.http.server.egg-info/top_level.txt
aio/http/__init__.py
aio/http/server/__init__.py
aio/http/server/listen.py
aio/http/server/servers.py
aio/http/server/utils.py
aio/http/server/tests/__init__.py
aio/http/server/tests/test_server.py