Metadata-Version: 1.1
Name: aio.http.server
Version: 0.1.4
Summary: HTTP server for the aio asyncio framework
Home-page: http://github.com/phlax/aio.http.server
Author: Ryan Northey
Author-email: ryan@3ca.org.uk
License: GPL
Platform: UNKNOWN
Classifier: Development Status :: 4 - Beta
Classifier: Intended Audience :: Developers
Classifier: Programming Language :: Python :: 3.4
Classifier: Topic :: Software Development :: Libraries :: Python Modules
